django_email_gateway/__init__.py
django_email_gateway/receiving_mail.py
django_email_gateway/sending_mail.py
django_email_gateway-0.1.2.dist-info/DESCRIPTION.rst
django_email_gateway-0.1.2.dist-info/METADATA
django_email_gateway-0.1.2.dist-info/RECORD
django_email_gateway-0.1.2.dist-info/WHEEL
django_email_gateway-0.1.2.dist-info/metadata.json
django_email_gateway-0.1.2.dist-info/top_level.txt
django_ses_gateway/__init__.py
django_ses_gateway/receiving_mail.py
django_ses_gateway/sending_mail.py
