Metadata-Version: 2.0
Name: django-email-gateway
Version: 0.1.2
Summary: A django package which act as a gateway to send and receive email with amazon SES.
Home-page: https://github.com/MicroPyramid/django-email-gateway
Author: Micropyramid
Author-email: hello@micropyramid.com
License: UNKNOWN
Platform: UNKNOWN
Classifier: Environment :: Web Environment
Classifier: Framework :: Django
Classifier: Intended Audience :: Developers
Classifier: Operating System :: OS Independent
Classifier: License :: OSI Approved :: MIT License
Classifier: Programming Language :: Python
Classifier: Programming Language :: Python :: 2.7
Classifier: Programming Language :: Python :: 3
Classifier: Programming Language :: Python :: 3.2
Classifier: Programming Language :: Python :: 3.3
Classifier: Topic :: Internet :: WWW/HTTP
Classifier: Topic :: Internet :: WWW/HTTP :: Dynamic Content
Requires-Dist: django
Requires-Dist: boto
Requires-Dist: lxml
